{"text":"\n\u00a0 \u00a0 \u00a0The Graffiti Advisory Board shall have the duty to: \n\u00a0 \u00a0 \u00a0(a)\u00a0 \u00a0 \u00a0Prepare and submit to the Board of Supervisors and the Mayor a report every six months on graffiti as it affects neighborhoods and the downtown area of San Francisco, which shall include a review and evaluation of the services and programs in place to respond to graffiti, prevention strategies, and recommendations and plans as to a consolidated program of public and private efforts; \n\u00a0 \u00a0 \u00a0(b)\u00a0 \u00a0 \u00a0Advise about the coordination of information, activities and goals among existing programs funded by the City and County and privately sponsored programs; \n\u00a0 \u00a0 \u00a0(c)\u00a0 \u00a0 \u00a0Advise about improving the efficiency in the provision of graffiti enforcement, prevention and clean-up services.\n(Added by Ord. 353-93, App. 11\/12\/93)\n\n","heading":{"title":"5","chaptersection":"172","identifier":"5.172","catch_text":"PURPOSE AND DUTIES."},"chapter":{"identifier":"5","text":"COMMITTEES\r\r"}}